furniture/__init__.py
furniture/animation.py
furniture/geometry.py
furniture/renderer.py
furniture/shortcuts.py
furniture/vfont.py
furniture-0.2.3.dist-info/LICENSE
furniture-0.2.3.dist-info/METADATA
furniture-0.2.3.dist-info/WHEEL
furniture-0.2.3.dist-info/entry_points.txt
furniture-0.2.3.dist-info/top_level.txt
furniture-0.2.3.dist-info/RECORD
