Metadata-Version: 2.1
Name: furniture
Version: 0.2.3
Summary: Typesetting and layout utilities for drawing and animating in DrawBot
Home-page: https://github.com/stenson/furniture
Author: Rob Stenson
Author-email: rob.stenson@gmail.com
License: UNKNOWN
Platform: UNKNOWN
Classifier: Programming Language :: Python :: 3
Classifier: License :: OSI Approved :: MIT License
Classifier: Operating System :: OS Independent
